[
    {
      "word": "adventure", 
      "audio": "https://clixplatform.tiss.edu/media/b/c/9/e99b835a7a598d31a16ffefdf1511a11a68097c9d8873b134320182eb3ec2", 
      "meaning": "something new and full of surprises", 
      "example": "School can be an adventure.",
      "hindi": "उत्साहवर्धक",
      "telugu" : "సాహస"
      
    },
      {
      "word": "aimed", 
      "audio": "https://clixplatform.tiss.edu/media/7/0/d/a295cf6ad1a03c9bd309fe3a532407622c215840f870ae9727fd753000530", 
      "meaning": "pointed at something", 
      "example": "Tara aimed her camera and clicked.",
      "hindi": "निशाना लगाना",
      "telugu" : "లక్ష్యంతో"
      
    },
    {
      "word": "xyz", 
      "audio": "https://clixplatform.tiss.edu/media/7/0/d/a295cf6ad1a03c9bd309fe3a532407622c215840f870ae9727fd753000530", 
      "meaning": "pointed at something", 
      "example": "Tara aimed her camera and clicked.",
      "hindi": "निशाना लगाना",
      "telugu" : "లక్ష్యంతో"
      
    }
]